customGPTBW/__init__.py
customGPTBW/struct_gpthelper.py
customGPTBW-0.1.5.dist-info/METADATA
customGPTBW-0.1.5.dist-info/WHEEL
customGPTBW-0.1.5.dist-info/top_level.txt
customGPTBW-0.1.5.dist-info/RECORD
