Metadata-Version: 2.1
Name: customGPTBW
Version: 0.1.5
Summary: A private module for dataset loading and GPT training.
Author: Boring._.wicked
Classifier: Programming Language :: Python :: 3
Classifier: License :: OSI Approved :: MIT License
Requires-Dist: tensorflow
Requires-Dist: transformers
Requires-Dist: tqdm
Requires-Dist: psutil
Requires-Dist: huggingface-hub
Requires-Dist: datasets
Requires-Dist: numpy
